{"arch_packages":"arm_cortex-a15_neon-vfpv4","default_packages":["base-files","busybox","ca-bundle","dnsmasq","dropbear","firewall4","fstools","kmod-ata-ahci","kmod-ata-ahci-platform","kmod-ath10k-ct","kmod-gpio-button-hotplug","kmod-leds-gpio","kmod-nft-offload","kmod-phy-qcom-ipq806x-usb","kmod-usb-dwc3-qcom","kmod-usb-ledtrig-usbport","kmod-usb-ohci","kmod-usb2","kmod-usb3","libc","libgcc","libustream-mbedtls","logd","mtd","netifd","nftables","odhcp6c","odhcpd-ipv6only","opkg","ppp","ppp-mod-pppoe","procd","procd-seccomp","procd-ujail","swconfig","uboot-envtools","uci","uclient-fetch","urandom-seed","urngd","wpad-basic-mbedtls"],"metadata_version":1,"profiles":{"nec_wg2600hp":{"device_packages":["ath10k-firmware-qca99x0-ct"],"image_prefix":"openwrt-ipq806x-generic-nec_wg2600hp","images":[{"filesystem":"initramfs","name":"openwrt-ipq806x-generic-nec_wg2600hp-initramfs-uImage","sha256":"9a7d11818be2ac4c7978ffb6aaee02b57262474dbc4834c383c9b233656b47ba","sha256_unsigned":"9a7d11818be2ac4c7978ffb6aaee02b57262474dbc4834c383c9b233656b47ba","type":"kernel"},{"filesystem":"squashfs","name":"openwrt-ipq806x-generic-nec_wg2600hp-squashfs-sysupgrade.bin","sha256":"f9ba17b54125c2b97f1f9d740215436dc14a99eba94c595dc0275a05d7f134a2","sha256_unsigned":"883d2151126b395f886dfb46ca5c82603f295dd630e1004732707025bb216c40","type":"sysupgrade"}],"supported_devices":["nec,wg2600hp"],"titles":[{"model":"Aterm WG2600HP","vendor":"NEC"}]}},"source_date_epoch":1711145382,"target":"ipq806x/generic","version_code":"r23809-234f1a2efa","version_number":"23.05.3"}